mcp_math_tools/__init__.py
mcp_math_tools/eigen.py
mcp_math_tools/matrix.py
mcp_math_tools/quadratic.py
mcp_math_tools-0.1.0.dist-info/METADATA
mcp_math_tools-0.1.0.dist-info/WHEEL
mcp_math_tools-0.1.0.dist-info/top_level.txt
mcp_math_tools-0.1.0.dist-info/RECORD
