Metadata-Version: 2.4
Name: mcp_math_tools
Version: 0.1.0
Summary: A collection of MCP-compatible math tools (matrix, quadratic, eigen)
Author-email: Poojitha29 <poojitha.mm@thoughtclan.com>
License: MIT
Requires-Python: >=3.8
Requires-Dist: numpy
Requires-Dist: sympy
